ssb/__init__.py
ssb-0.0.0.dist-info/METADATA
ssb-0.0.0.dist-info/WHEEL
ssb-0.0.0.dist-info/top_level.txt
ssb-0.0.0.dist-info/RECORD
